lib/__init__.py
lib/bb.py
lib/bitbucketCLI/CmdIssue.py
lib/bitbucketCLI/CmdPullRequest.py
lib/bitbucketCLI/Config.py
lib/bitbucketCLI/UserAgent.py
lib/bitbucketCLI/Utils.py
lib/bitbucketCLI/__init__.py
thvu_bitbucket_cli-1.dist-info/LICENSE
thvu_bitbucket_cli-1.dist-info/METADATA
thvu_bitbucket_cli-1.dist-info/WHEEL
thvu_bitbucket_cli-1.dist-info/entry_points.txt
thvu_bitbucket_cli-1.dist-info/top_level.txt
thvu_bitbucket_cli-1.dist-info/RECORD
