Metadata-Version: 2.1
Name: thvu-bitbucket-cli
Version: 1
Summary: UNKNOWN
Home-page: https://github.com/thvu11/Bitbucket-CLI.git
Author: UNKNOWN
Author-email: UNKNOWN
License: MIT
Platform: UNKNOWN
Classifier: License :: OSI Approved :: Python Software Foundation License
Requires-Dist: click
Requires-Dist: requests
